{
  "graph_id": "counter",
  "source_path": "examples/counter/source.bn",
  "source_hash": 11176993741951227581,
  "source_bindings": [
    {
      "source_id": "StoreSourcesIncrementButtonEventPress",
      "path": "store.sources.increment_button.event.press",
      "shape": "SourceMarker",
      "dynamic": false
    }
  ],
  "nodes": [
    {
      "node": "DocumentText",
      "kind": "render.text",
      "shape": "Text",
      "source_span": "examples/counter/source.bn:document"
    },
    {
      "node": "Counter",
      "kind": "monitor.value",
      "shape": "Text",
      "source_span": "examples/counter/source.bn:document"
    },
    {
      "node": "StoreSourcesIncrementButtonEventPress",
      "kind": "source.leaf",
      "shape": "SourceMarker",
      "source_span": "examples/counter/source.bn:store.sources.increment_button.event.press"
    }
  ],
  "operators": [
    {
      "node": "SourceLeaf",
      "kind": "SourceLeaf",
      "inputs": [],
      "output": "SourceLeaf",
      "order": 0
    },
    {
      "node": "Then",
      "kind": "Then",
      "inputs": [],
      "output": "Then",
      "order": 10
    },
    {
      "node": "ThenConst",
      "kind": "ThenConst",
      "inputs": [],
      "output": "ThenConst",
      "order": 11
    },
    {
      "node": "LibraryCall",
      "kind": "LibraryCall",
      "inputs": [],
      "output": "LibraryCall",
      "order": 70
    },
    {
      "node": "RenderSink",
      "kind": "RenderSink",
      "inputs": [],
      "output": "RenderSink",
      "order": 100
    },
    {
      "node": "MonitorTap",
      "kind": "MonitorTap",
      "inputs": [],
      "output": "MonitorTap",
      "order": 101
    }
  ],
  "monitor_node": "Counter",
  "render_node": "DocumentText",
  "initial_text": "0",
  "dd_plan": {
    "CountInputEvents": {
      "initial": 0
    }
  },
  "physical_scene": false
}